psc_api_public/__init__.py
psc_api_public/psc_api.py
psc_api_public/test-psc_api.py
psc_api_pub-0.0.22.dist-info/METADATA
psc_api_pub-0.0.22.dist-info/WHEEL
psc_api_pub-0.0.22.dist-info/top_level.txt
psc_api_pub-0.0.22.dist-info/RECORD
