Metadata-Version: 2.1
Name: psc-api-pub
Version: 0.0.22
Summary: psc api for public
Home-page: http://www.alarmchang.com
Author: AlarmChang
Author-email: AlarmChang@moldex3d.com
License: LGPL
Keywords: easyredmine
Platform: UNKNOWN
